mkconvert/__init__.py
mkconvert/extensions.py
mkconvert/html_to_md/__init__.py
mkconvert/html_to_md/base.py
mkconvert/html_to_md/factory.py
mkconvert/html_to_md/htmd_converter.py
mkconvert/html_to_md/markdownify_converter.py
mkconvert/parsers/__init__.py
mkconvert/parsers/base_parser.py
mkconvert/parsers/comrak_parser/__init__.py
mkconvert/parsers/comrak_parser/parser.py
mkconvert/parsers/github_api_parser/__init__.py
mkconvert/parsers/github_api_parser/parser.py
mkconvert/parsers/markdown2_parser/__init__.py
mkconvert/parsers/markdown2_parser/parser.py
mkconvert/parsers/markdown_it_pyrs_parser/__init__.py
mkconvert/parsers/markdown_it_pyrs_parser/parser.py
mkconvert/parsers/marko_parser/__init__.py
mkconvert/parsers/marko_parser/parser.py
mkconvert/parsers/mistletoe_parser/__init__.py
mkconvert/parsers/mistune_parser/__init__.py
mkconvert/parsers/mistune_parser/parser.py
mkconvert/parsers/parser.py
mkconvert/parsers/pyromark_parser/__init__.py
mkconvert/parsers/pyromark_parser/parser.py
mkconvert/parsers/python_markdown_parser/__init__.py
mkconvert/parsers/python_markdown_parser/parser.py
mkconvert/post_processors/__init__.py
mkconvert/post_processors/base.py
mkconvert/post_processors/prettify.py
mkconvert/post_processors/registry.py
mkconvert/post_processors/sanitizer.py
mkconvert/pre_processors/__init__.py
mkconvert/pre_processors/admonition_converter.py
mkconvert/pre_processors/base.py
mkconvert/pre_processors/registry.py
mkconvert/py.typed
mkconvert/sanitizers/__init__.py
mkconvert/sanitizers/base.py
mkconvert/sanitizers/bleach_sanitizer.py
mkconvert/sanitizers/factory.py
mkconvert/sanitizers/nh3_sanitizer.py
mkconvert/tree_processors/__init__.py
mkconvert/tree_processors/base.py
mkconvert/tree_processors/extract_title.py
mkconvert/tree_processors/extract_title_lxml.py
mkconvert/tree_processors/registry.py
mkconvert-1.0.0.dist-info/WHEEL
mkconvert-1.0.0.dist-info/METADATA
mkconvert-1.0.0.dist-info/RECORD
