Metadata-Version: 2.3
Name: mkconvert
Version: 1.0.0
Summary: Markdown-HTML converters
Keywords: 
Author: Philipp Temminghoff
Author-email: Philipp Temminghoff <philipptemminghoff@googlemail.com>
License: MIT License
Classifier: Development Status :: 4 - Beta
Classifier: Framework :: Pydantic
Classifier: Framework :: Pydantic :: 2
Classifier: Intended Audience :: Developers
Classifier: Operating System :: OS Independent
Classifier: Programming Language :: Python :: 3
Classifier: Programming Language :: Python :: 3 :: Only
Classifier: Programming Language :: Python :: 3.12
Classifier: Programming Language :: Python :: 3.13
Classifier: Programming Language :: Python :: 3.14
Classifier: Topic :: Documentation
Classifier: Topic :: Software Development
Classifier: Topic :: Utilities
Classifier: Typing :: Typed
Requires-Dist: pydantic
Requires-Dist: schemez
Requires-Dist: comrak ; python_full_version < '3.14' and extra == 'comrak'
Requires-Dist: htmd-py ; extra == 'htmd-py'
Requires-Dist: lxml ; python_full_version < '3.14' and extra == 'lxml'
Requires-Dist: markdown ; extra == 'markdown'
Requires-Dist: pymdown-extensions>=10.12 ; extra == 'markdown'
Requires-Dist: markdown-it-pyrs ; extra == 'markdown-it-pyrs'
Requires-Dist: markdown2 ; extra == 'markdown2'
Requires-Dist: markdownify ; extra == 'markdownify'
Requires-Dist: marko ; extra == 'marko'
Requires-Dist: mistune ; extra == 'mistune'
Requires-Dist: nh3 ; extra == 'nh3'
Requires-Dist: pyromark ; python_full_version < '3.14' and extra == 'pyromark'
Requires-Python: >=3.13
Project-URL: Code coverage, https://app.codecov.io/gh/phil65/mkconvert
Project-URL: Discussions, https://github.com/phil65/mkconvert/discussions
Project-URL: Documentation, https://phil65.github.io/mkconvert/
Project-URL: Issues, https://github.com/phil65/mkconvert/issues
Project-URL: Source, https://github.com/phil65/mkconvert
Provides-Extra: comrak
Provides-Extra: htmd-py
Provides-Extra: lxml
Provides-Extra: markdown
Provides-Extra: markdown-it-pyrs
Provides-Extra: markdown2
Provides-Extra: markdownify
Provides-Extra: marko
Provides-Extra: mistune
Provides-Extra: nh3
Provides-Extra: pyromark
